chromdetect/__init__.py
chromdetect/__main__.py
chromdetect/assembly_report.py
chromdetect/cli.py
chromdetect/compare.py
chromdetect/core.py
chromdetect/html_report.py
chromdetect/patterns.py
chromdetect-0.5.0.dist-info/METADATA
chromdetect-0.5.0.dist-info/WHEEL
chromdetect-0.5.0.dist-info/entry_points.txt
chromdetect-0.5.0.dist-info/licenses/LICENSE
chromdetect-0.5.0.dist-info/RECORD
