Metadata-Version: 2.4
Name: chromdetect
Version: 0.5.0
Summary: Detect chromosome-level scaffolds in genome assemblies with inconsistent naming conventions
Project-URL: Homepage, https://github.com/shandley/chromdetect
Project-URL: Documentation, https://github.com/shandley/chromdetect#readme
Project-URL: Repository, https://github.com/shandley/chromdetect.git
Project-URL: Issues, https://github.com/shandley/chromdetect/issues
Project-URL: Changelog, https://github.com/shandley/chromdetect/blob/main/CHANGELOG.md
Author-email: Scott Handley <handley.scott@gmail.com>
License-Expression: MIT
License-File: LICENSE
Keywords: VGP,bioinformatics,chromosome,genome-assembly,genomics,karyotype,scaffolds
Classifier: Development Status :: 4 - Beta
Classifier: Environment :: Console
Classifier: Intended Audience :: Science/Research
Classifier: License :: OSI Approved :: MIT License
Classifier: Operating System :: OS Independent
Classifier: Programming Language :: Python :: 3
Classifier: Programming Language :: Python :: 3.9
Classifier: Programming Language :: Python :: 3.10
Classifier: Programming Language :: Python :: 3.11
Classifier: Programming Language :: Python :: 3.12
Classifier: Topic :: Scientific/Engineering :: Bio-Informatics
Requires-Python: >=3.9
Provides-Extra: dev
Requires-Dist: mypy>=1.0; extra == 'dev'
Requires-Dist: pytest-cov>=4.0; extra == 'dev'
Requires-Dist: pytest>=7.0; extra == 'dev'
Requires-Dist: ruff>=0.1; extra == 'dev'
